uwu_python-0.1.3.dist-info/METADATA
uwu_python-0.1.3.dist-info/WHEEL
uwu_python/__init__.py
uwu_python/uwu_python.cpython-310-x86_64-linux-gnu.so
uwu_python-0.1.3.dist-info/RECORD
